README.md
setup.cfg
setup.py
limiter/__init__.py
limiter/counter.py
limiter/rate_limiter.py
python_throttle.egg-info/PKG-INFO
python_throttle.egg-info/SOURCES.txt
python_throttle.egg-info/dependency_links.txt
python_throttle.egg-info/requires.txt
python_throttle.egg-info/top_level.txt
test/test_counter.py
test/test_limiter.py