Metadata-Version: 1.2
Name: python-throttle
Version: 0.1.9
Summary: Super naive python redis limiter
Home-page: https://github.com/soulomoon/python-throttle
Author: soulomoon
Author-email: fwy996602672@gmail.com
License: UNKNOWN
Keywords: throttle limiter redis counter timer middleware
Platform: UNKNOWN
Classifier: Intended Audience :: Developers
Classifier: License :: OSI Approved :: MIT License
Classifier: Programming Language :: Python
Classifier: Programming Language :: Python :: 3.5
Classifier: Programming Language :: Python :: 3.6
Classifier: Programming Language :: Python :: 3.7
Classifier: Programming Language :: Python :: Implementation :: CPython
Classifier: Topic :: Software Development :: Libraries :: Python Modules
Requires-Python: >=3.5
